juneja_codebase/__init__.py
juneja_codebase/main.py
juneja_codebase/templates/compiler_design/AnshJuneja_Practical10_CD.l
juneja_codebase/templates/compiler_design/AnshJuneja_Practical10_CD.y
juneja_codebase/templates/compiler_design/AnshJuneja_Practical11_CD.l
juneja_codebase/templates/compiler_design/AnshJuneja_Practical11_CD.y
juneja_codebase/templates/compiler_design/AnshJuneja_Practical12_CD.l
juneja_codebase/templates/compiler_design/AnshJuneja_Practical12_CD.y
juneja_codebase/templates/compiler_design/AnshJuneja_Practical13_CD.l
juneja_codebase/templates/compiler_design/AnshJuneja_Practical13_CD.y
juneja_codebase/templates/compiler_design/AnshJuneja_Practical1_CD.l
juneja_codebase/templates/compiler_design/AnshJuneja_Practical2_CD.l
juneja_codebase/templates/compiler_design/AnshJuneja_Practical3_CD.l
juneja_codebase/templates/compiler_design/AnshJuneja_Practical4_CD.l
juneja_codebase/templates/compiler_design/AnshJuneja_Practical5_CD.l
juneja_codebase/templates/compiler_design/AnshJuneja_Practical6_CD.l
juneja_codebase/templates/compiler_design/AnshJuneja_Practical7_CD.l
juneja_codebase/templates/compiler_design/AnshJuneja_Practical8_CD.l
juneja_codebase/templates/compiler_design/AnshJuneja_Practical9_CD.l
juneja_codebase/templates/compiler_design/AnshJuneja_Practical9_CD.y
juneja_codebase/templates/deep_learning/Denoised_Autoencoders.ipynb
juneja_codebase/templates/deep_learning/Fashion_Mnist_DenseNet201_VGG19_PreTModel.ipynb
juneja_codebase/templates/deep_learning/Image_Compression_Autoencoders.ipynb
juneja_codebase/templates/deep_learning/boston_housing.ipynb
juneja_codebase/templates/deep_learning/cnn_fashionmnist.ipynb
juneja_codebase/templates/deep_learning/posneg_imdb_ffnn..ipynb
juneja_codebase/templates/deep_learning/reuters.ipynb
juneja_codebase/templates/deep_learning/rnnlstm_timeseries_imdb.ipynb
juneja_codebase/templates/social_network_analysis/1_try.ipynb
juneja_codebase/templates/social_network_analysis/2_try.ipynb
juneja_codebase-4.0.0.dist-info/LICENSE
juneja_codebase-4.0.0.dist-info/METADATA
juneja_codebase-4.0.0.dist-info/WHEEL
juneja_codebase-4.0.0.dist-info/entry_points.txt
juneja_codebase-4.0.0.dist-info/top_level.txt
juneja_codebase-4.0.0.dist-info/RECORD
