Metadata-Version: 2.1
Name: juneja_codebase
Version: 4.0.0
Summary: CLI tool to generate academic practical code files for Compiler Design, Data Structures, OS, and DBMS
Home-page: UNKNOWN
Author: AJ
License: UNKNOWN
Platform: UNKNOWN
Classifier: Programming Language :: Python :: 3
Classifier: License :: OSI Approved :: MIT License
Classifier: Operating System :: OS Independent
Classifier: Intended Audience :: Education
Requires-Python: >=3.6
License-File: LICENSE
